topsis/101703373-topsis.py
101703373_topsis-1.0.0.dist-info/LICENSE
101703373_topsis-1.0.0.dist-info/METADATA
101703373_topsis-1.0.0.dist-info/WHEEL
101703373_topsis-1.0.0.dist-info/entry_points.txt
101703373_topsis-1.0.0.dist-info/top_level.txt
101703373_topsis-1.0.0.dist-info/RECORD
