Metadata-Version: 2.1
Name: 101703373-topsis
Version: 1.0.0
Summary: A Python package to get optimal solutiion.
Home-page: UNKNOWN
Author: Nikhil Vyas
Author-email: vyasnikhil30@gmail.com
License: MIT
Platform: UNKNOWN
Classifier: License :: OSI Approved :: MIT License
Classifier: Programming Language :: Python :: 3
Classifier: Programming Language :: Python :: 3.7
Requires-Dist: sys
Requires-Dist: os
Requires-Dist: pandas
Requires-Dist: math
Requires-Dist: numpy
